kozmoserver_sklearn/__init__.py
kozmoserver_sklearn/sklearn.py
kozmoserver_sklearn/version.py
kozmoserver_sklearn-0.1.0.dev1.dist-info/LICENSE
kozmoserver_sklearn-0.1.0.dev1.dist-info/METADATA
kozmoserver_sklearn-0.1.0.dev1.dist-info/WHEEL
kozmoserver_sklearn-0.1.0.dev1.dist-info/RECORD
